pyosrs/__init__.py
pyosrs/client.py
pyosrs/enums.py
pyosrs/exceptions.py
pyosrs/models.py
pyosrs/utils.py
pyosrs-0.0.8.dist-info/LICENSE
pyosrs-0.0.8.dist-info/METADATA
pyosrs-0.0.8.dist-info/WHEEL
pyosrs-0.0.8.dist-info/RECORD
