Metadata-Version: 2.1
Name: pyosrs
Version: 0.0.8
Summary: A Python library for Oldschool RuneScape.
Home-page: https://github.com/phongse/pyosrs
License: LGPL-3.0-only
Author: Phong Tran
Requires-Python: >=3.8,<4.0
Classifier: License :: OSI Approved :: GNU Lesser General Public License v3 (LGPLv3)
Classifier: Programming Language :: Python :: 3
Classifier: Programming Language :: Python :: 3.8
Classifier: Programming Language :: Python :: 3.9
Classifier: Programming Language :: Python :: 3.10
Classifier: Programming Language :: Python :: 3.11
Classifier: Programming Language :: Python :: 3.12
Requires-Dist: httpx (>=0.24.0,<0.25.0)
Requires-Dist: pydantic (>=1.10.7,<2.0.0)
Project-URL: Repository, https://github.com/phongse/pyosrs
